script_tracker/__init__.py
script_tracker/live-scraping-firebase-adminsdk-gck9g-011e4f00e1.json
script_tracker/script_tracker.py
script_tracker-0.0.1.dist-info/METADATA
script_tracker-0.0.1.dist-info/WHEEL
script_tracker-0.0.1.dist-info/top_level.txt
script_tracker-0.0.1.dist-info/RECORD
