Metadata-Version: 2.1
Name: script-tracker
Version: 0.0.1
Summary: Script Tacker provides an Android and Ios mobile application based dashboard to perform live tracking of your scripts. Currently this is only supporting python. Users can track the progress of their scripts from anywhere. Mobile applications are created using Flutter platform and server side is managed using Firebase.
Home-page: https://github.com/asad1996172/Script-Tracker
Author: UNKNOWN
Author-email: asad007mahmood@gmail.com, ahmadzee26@gmail.com
License: MIT
Download-URL: https://github.com/asad1996172/Script-Tracker
Platform: UNKNOWN
Requires-Dist: requests
Requires-Dist: firebase-admin
